tap_megaphone/__init__.py
tap_megaphone/auth.py
tap_megaphone/client.py
tap_megaphone/schemas/advertiser_categories.schema.json
tap_megaphone/schemas/advertisers.schema.json
tap_megaphone/schemas/agencies.schema.json
tap_megaphone/schemas/campaign_order_advertisements.schema.json
tap_megaphone/schemas/campaign_orders.schema.json
tap_megaphone/schemas/campaigns.schema.json
tap_megaphone/schemas/countries.schema.json
tap_megaphone/schemas/devices.schema.json
tap_megaphone/schemas/dmas.schema.json
tap_megaphone/schemas/episodes.schema.json
tap_megaphone/schemas/iab_advertiser_categories.schema.json
tap_megaphone/schemas/networks.schema.json
tap_megaphone/schemas/nielsen_segments.schema.json
tap_megaphone/schemas/organization_tags.schema.json
tap_megaphone/schemas/podcasts.schema.json
tap_megaphone/schemas/promo_order_advertisements.schema.json
tap_megaphone/schemas/promo_orders.schema.json
tap_megaphone/schemas/regions.schema.json
tap_megaphone/streams.py
tap_megaphone/tap.py
tap_megaphone/tests/__init__.py
tap_megaphone/tests/test_core.py
tap_megaphone-0.1.2.dist-info/entry_points.txt
tap_megaphone-0.1.2.dist-info/LICENSE.md
tap_megaphone-0.1.2.dist-info/WHEEL
tap_megaphone-0.1.2.dist-info/METADATA
tap_megaphone-0.1.2.dist-info/RECORD
