Metadata-Version: 2.1
Name: tap-megaphone
Version: 0.1.2
Summary: `tap-megaphone` is a Singer tap for Megaphone, built with the Meltano SDK for Singer Taps.
License: Apache 2.0
Keywords: ELT,Megaphone
Author: Joy Yu
Requires-Python: >=3.6.2,<3.11
Classifier: License :: Other/Proprietary License
Classifier: Programming Language :: Python :: 3
Classifier: Programming Language :: Python :: 3.10
Classifier: Programming Language :: Python :: 3.7
Classifier: Programming Language :: Python :: 3.8
Classifier: Programming Language :: Python :: 3.9
Requires-Dist: pendulum (>=2.1.2,<3.0.0)
Requires-Dist: requests (>=2.25.1,<3.0.0)
Requires-Dist: singer-sdk (>=0.4.1,<0.5.0)
